portf/__init__.py
portf/builder.py
portf/static/data.txt
portf/static/favicon.ico
portf/static/css/aos.css
portf/static/css/bootstrap.min.css
portf/static/css/main.css
portf/static/images/cc-bg-1.jpg
portf/static/images/map.JPG
portf/static/images/profile.png
portf/static/images/staticmap.png
portf/static/js/aos.js
portf/static/js/now-ui-kit.js
portf/static/js/core/bootstrap.min.js
portf/static/js/core/jquery.3.2.1.min.js
portf/static/js/core/popper.min.js
portf/static/js/plugins/bootstrap-datepicker.js
portf/static/js/plugins/bootstrap-switch.js
portf/static/js/plugins/jquery.sharrre.js
portf/static/js/plugins/nouislider.min.js
portf/static/scripts/main.js
portf/templates/index.html
portf-0.1.1.dist-info/LICENCE
portf-0.1.1.dist-info/METADATA
portf-0.1.1.dist-info/WHEEL
portf-0.1.1.dist-info/top_level.txt
portf-0.1.1.dist-info/RECORD
