Metadata-Version: 2.1
Name: portf
Version: 0.1.1
Summary: A pyhton packages for creating portfolio site within minutes!
Home-page: https://github.com/Saigenix/portf
Author: Saigenix
Author-email: sainathkumar805@gmail.com
Project-URL: Bug Tracker, https://github.com/Saigenix/portf/issues
Classifier: Programming Language :: Python :: 3
Classifier: License :: OSI Approved :: MIT License
Classifier: Operating System :: OS Independent
Requires-Python: >=3.6
License-File: LICENCE
Requires-Dist: flask
